sprockets.mixins.statsd-1.4.0-py3.7-nspkg.pth
sprockets/mixins/statsd/__init__.py
sprockets.mixins.statsd-1.4.0.dist-info/LICENSE
sprockets.mixins.statsd-1.4.0.dist-info/METADATA
sprockets.mixins.statsd-1.4.0.dist-info/WHEEL
sprockets.mixins.statsd-1.4.0.dist-info/namespace_packages.txt
sprockets.mixins.statsd-1.4.0.dist-info/top_level.txt
sprockets.mixins.statsd-1.4.0.dist-info/RECORD
